pyjangle_json_logging/__init__.py
pyjangle_json_logging/logging.py
pyjangle_json_logging-0.1.0b0.dist-info/LICENSE
pyjangle_json_logging-0.1.0b0.dist-info/METADATA
pyjangle_json_logging-0.1.0b0.dist-info/WHEEL
pyjangle_json_logging-0.1.0b0.dist-info/top_level.txt
pyjangle_json_logging-0.1.0b0.dist-info/RECORD
