Metadata-Version: 2.1
Name: pyjangle-json-logging
Version: 0.1.0b0
Summary: JSON logging for PyJangle
Author-email: Bellstein Labs LLC <bellstein.labs@gmail.com>
License: MIT License
Project-URL: Homepage, https://github.com/BellsteinLabs/pyJangle_json_logging
Keywords: logging,pyjangle,jangle
Classifier: License :: OSI Approved :: MIT License
Classifier: Programming Language :: Python
Classifier: Programming Language :: Python :: 3
Classifier: Development Status :: 4 - Beta
Classifier: Intended Audience :: Developers
Classifier: Natural Language :: English
Classifier: Operating System :: OS Independent
Classifier: Topic :: Software Development :: Libraries
Classifier: Topic :: Software Development :: Libraries :: Application Frameworks
Requires-Python: >=3.10
License-File: LICENSE
Requires-Dist: pyjangle ==0.*
